cellfolding/__init__.py
cellfolding/static/README.md
cellfolding/static/description.yaml
cellfolding/static/index.js
nbextension_cellfolding-0.0.3.dist-info/METADATA
nbextension_cellfolding-0.0.3.dist-info/WHEEL
nbextension_cellfolding-0.0.3.dist-info/top_level.txt
nbextension_cellfolding-0.0.3.dist-info/RECORD
