Metadata-Version: 2.1
Name: nbextension-cellfolding
Version: 0.0.3
Summary: UNKNOWN
Home-page: https://github.com/BenedictWilkinsAI/cellfolding
Author: Benedict Wilkins
Author-email: brjw@hotmail.co.uk
License: GNU General Public License v3 (GPLv3)T
Platform: UNKNOWN
Classifier: Programming Language :: Python :: 3.7
Classifier: Development Status :: 2 - Pre-Alpha
Classifier: License :: OSI Approved :: GNU General Public License v3 (GPLv3)
Classifier: Operating System :: OS Independent
Requires-Dist: jupyter
